ai_shell/__init__.py
ai_shell/demo_mode.py
ai_shell/executor.py
ai_shell/llm.py
ai_shell/main.py
ai_shell/safety.py
ai_shell_cli-0.1.0.dist-info/licenses/LICENSE
ai_shell_cli-0.1.0.dist-info/METADATA
ai_shell_cli-0.1.0.dist-info/WHEEL
ai_shell_cli-0.1.0.dist-info/entry_points.txt
ai_shell_cli-0.1.0.dist-info/top_level.txt
ai_shell_cli-0.1.0.dist-info/RECORD
