Metadata-Version: 2.4
Name: ai-shell-cli
Version: 0.1.0
Summary: AI-Powered Interactive Shell - Convert natural language to shell commands
Home-page: https://github.com/ai-shell/ai-shell
Author: AI-shell Team
Author-email: AI-shell Team <contact@ai-shell.dev>
Maintainer-email: AI-shell Team <contact@ai-shell.dev>
License: MIT
Project-URL: Homepage, https://github.com/ai-shell/ai-shell
Project-URL: Documentation, https://github.com/ai-shell/ai-shell#readme
Project-URL: Repository, https://github.com/ai-shell/ai-shell
Project-URL: Issues, https://github.com/ai-shell/ai-shell/issues
Keywords: shell,ai,cli,terminal,automation,command-line
Classifier: Development Status :: 4 - Beta
Classifier: Intended Audience :: Developers
Classifier: Intended Audience :: System Administrators
Classifier: License :: OSI Approved :: MIT License
Classifier: Operating System :: OS Independent
Classifier: Programming Language :: Python :: 3
Classifier: Programming Language :: Python :: 3.8
Classifier: Programming Language :: Python :: 3.9
Classifier: Programming Language :: Python :: 3.10
Classifier: Programming Language :: Python :: 3.11
Classifier: Programming Language :: Python :: 3.12
Classifier: Topic :: System :: Shells
Classifier: Topic :: System :: Systems Administration
Classifier: Topic :: Utilities
Requires-Python: >=3.8
License-File: LICENSE
Requires-Dist: requests>=2.31.0
Requires-Dist: rich>=13.0.0
Requires-Dist: python-dotenv>=1.0.0
Provides-Extra: dev
Requires-Dist: pytest>=7.0.0; extra == "dev"
Requires-Dist: pytest-cov>=4.0.0; extra == "dev"
Requires-Dist: black>=23.0.0; extra == "dev"
Requires-Dist: flake8>=6.0.0; extra == "dev"
Requires-Dist: mypy>=1.0.0; extra == "dev"
Dynamic: author
Dynamic: home-page
Dynamic: license-file
Dynamic: requires-python
